<?xml version="1.0" encoding="UTF-8"?>
<!DOCTYPE mapper PUBLIC "-//mybatis.org//DTD Mapper 3.0//EN" "http://mybatis.org/dtd/mybatis-3-mapper.dtd">
<mapper namespace="com.itdr.dao.ShoppingMapper">
  <resultMap id="BaseResultMap" type="com.itdr.pojo.Shopping">
    <!--
      WARNING - @mbg.generated
      This element is automatically generated by MyBatis Generator, do not modify.
      This element was generated on Mon Oct 29 15:48:44 CST 2018.
    -->
    <id column="id" jdbcType="INTEGER" property="id" />
    <result column="user_id" jdbcType="INTEGER" property="userId" />
    <result column="receiver_name" jdbcType="VARCHAR" property="receiverName" />
    <result column="receiver_phone" jdbcType="VARCHAR" property="receiverPhone" />
    <result column="receiver_mobile" jdbcType="VARCHAR" property="receiverMobile" />
    <result column="receiver_province" jdbcType="VARCHAR" property="receiverProvince" />
    <result column="receiver_city" jdbcType="VARCHAR" property="receiverCity" />
    <result column="receiver_district" jdbcType="VARCHAR" property="receiverDistrict" />
    <result column="receiver_address" jdbcType="VARCHAR" property="receiverAddress" />
    <result column="receiver_zip" jdbcType="VARCHAR" property="receiverZip" />
    <result column="create_time" jdbcType="TIMESTAMP" property="createTime" />
    <result column="update_time" jdbcType="TIMESTAMP" property="updateTime" />
  </resultMap>
  <delete id="deleteByPrimaryKey" parameterType="java.lang.Integer">
    <!--
      WARNING - @mbg.generated
      This element is automatically generated by MyBatis Generator, do not modify.
      This element was generated on Mon Oct 29 15:48:44 CST 2018.
    -->
    delete from neuedu_shopping
    where id = #{id,jdbcType=INTEGER}
  </delete>
  <insert id="insert" parameterType="com.itdr.pojo.Shopping" useGeneratedKeys="true" keyProperty="id">
    <!--
      WARNING - @mbg.generated
      This element is automatically generated by MyBatis Generator, do not modify.
      This element was generated on Mon Oct 29 15:48:44 CST 2018.
    -->
    insert into neuedu_shopping (user_id, receiver_name,
      receiver_phone, receiver_mobile, receiver_province, 
      receiver_city, receiver_district, receiver_address, 
      receiver_zip, create_time, update_time
      )
    values ( #{userId,jdbcType=INTEGER}, #{receiverName,jdbcType=VARCHAR},
      #{receiverPhone,jdbcType=VARCHAR}, #{receiverMobile,jdbcType=VARCHAR}, #{receiverProvince,jdbcType=VARCHAR}, 
      #{receiverCity,jdbcType=VARCHAR}, #{receiverDistrict,jdbcType=VARCHAR}, #{receiverAddress,jdbcType=VARCHAR}, 
      #{receiverZip,jdbcType=VARCHAR},now(), now()
      )
  </insert>
  <update id="updateByPrimaryKey" parameterType="com.itdr.pojo.Shopping" >
    <!--
      WARNING - @mbg.generated
      This element is automatically generated by MyBatis Generator, do not modify.
      This element was generated on Mon Oct 29 15:48:44 CST 2018.
    -->
    update neuedu_shopping
    set user_id = #{userId,jdbcType=INTEGER},
      receiver_name = #{receiverName,jdbcType=VARCHAR},
      receiver_phone = #{receiverPhone,jdbcType=VARCHAR},
      receiver_mobile = #{receiverMobile,jdbcType=VARCHAR},
      receiver_province = #{receiverProvince,jdbcType=VARCHAR},
      receiver_city = #{receiverCity,jdbcType=VARCHAR},
      receiver_district = #{receiverDistrict,jdbcType=VARCHAR},
      receiver_address = #{receiverAddress,jdbcType=VARCHAR},
      receiver_zip = #{receiverZip,jdbcType=VARCHAR},
      create_time = #{createTime,jdbcType=TIMESTAMP},
      update_time = #{updateTime,jdbcType=TIMESTAMP}
    where id = #{id,jdbcType=INTEGER}
  </update>
  <select id="selectByPrimaryKey" parameterType="java.lang.Integer" resultMap="BaseResultMap">
    <!--
      WARNING - @mbg.generated
      This element is automatically generated by MyBatis Generator, do not modify.
      This element was generated on Mon Oct 29 15:48:44 CST 2018.
    -->
    select id, user_id, receiver_name, receiver_phone, receiver_mobile, receiver_province, 
    receiver_city, receiver_district, receiver_address, receiver_zip, create_time, update_time
    from neuedu_shopping
    where id = #{id,jdbcType=INTEGER}
  </select>
  <select id="selectAll" resultMap="BaseResultMap">
    <!--
      WARNING - @mbg.generated
      This element is automatically generated by MyBatis Generator, do not modify.
      This element was generated on Mon Oct 29 15:48:44 CST 2018.
    -->
    select id, user_id, receiver_name, receiver_phone, receiver_mobile, receiver_province, 
    receiver_city, receiver_district, receiver_address, receiver_zip, create_time, update_time
    from neuedu_shopping
  </select>
  <delete id="deleteByuserIdAndShoppingId" parameterType="map" >
    delete from neuedu_shopping
    where id = #{shoppingId} and user_id=#{userId}
</delete>

  <update id="updateBySelectiveKey" parameterType="com.itdr.pojo.Shopping">
    update neuedu_shopping
    <set>
      <if test="receiverName!=null">
        receiver_name = #{receiverName,jdbcType=VARCHAR},
      </if>
      <if test="receiverPhone!=null">
        receiver_phone = #{receiverPhone,jdbcType=VARCHAR},
      </if>
      <if test="receiverMobile!=null">
        receiver_mobile = #{receiverMobile,jdbcType=VARCHAR},
      </if>
      <if test="receiverProvince!=null">
        receiver_province = #{receiverProvince,jdbcType=VARCHAR},
      </if>

      <if test="receiverCity!=null">
        receiver_city = #{receiverCity,jdbcType=VARCHAR},
      </if>
      <if test="receiverDistrict!=null">
        receiver_district = #{receiverDistrict,jdbcType=VARCHAR},
      </if>
      <if test="receiverAddress!=null">
        receiver_address = #{receiverAddress,jdbcType=VARCHAR},
      </if>
      <if test="receiverZip!=null">
        receiver_zip = #{receiverZip,jdbcType=VARCHAR},
      </if>
      update_time = now()
    </set>
    where user_id = #{userId,jdbcType=INTEGER} and id = #{id,jdbcType=INTEGER}
  </update>
</mapper>